picturebook_ai_selector/__init__.py
picturebook_ai_selector/example.py
picturebook_ai_selector/frontend/build/asset-manifest.json
picturebook_ai_selector/frontend/build/bootstrap.min.css
picturebook_ai_selector/frontend/build/index.html
picturebook_ai_selector/frontend/build/static/js/2.d82f61e7.chunk.js
picturebook_ai_selector/frontend/build/static/js/2.d82f61e7.chunk.js.LICENSE.txt
picturebook_ai_selector/frontend/build/static/js/2.d82f61e7.chunk.js.map
picturebook_ai_selector/frontend/build/static/js/main.3052046e.chunk.js
picturebook_ai_selector/frontend/build/static/js/main.3052046e.chunk.js.map
picturebook_ai_selector/frontend/build/static/js/runtime-main.3178c530.js
picturebook_ai_selector/frontend/build/static/js/runtime-main.3178c530.js.map
picturebook_ai_selector-0.0.1.dist-info/LICENSE
picturebook_ai_selector-0.0.1.dist-info/METADATA
picturebook_ai_selector-0.0.1.dist-info/WHEEL
picturebook_ai_selector-0.0.1.dist-info/top_level.txt
picturebook_ai_selector-0.0.1.dist-info/RECORD
